simple_menu_manager/__init__.py
simple_menu_manager/simple_menu.py
simple_menu_manager-0.0.3.dist-info/METADATA
simple_menu_manager-0.0.3.dist-info/WHEEL
simple_menu_manager-0.0.3.dist-info/licenses/LICENSE
simple_menu_manager-0.0.3.dist-info/RECORD
