Metadata-Version: 2.4
Name: simple_menu_manager
Version: 0.0.3
Summary: A simple menu manager package.
Project-URL: Homepage, https://github.com/D-Edward-Scott/Simple-Menu-Manager
Project-URL: Issues, https://github.com/D-Edward-Scott/Simple-Menu-Manager/issues
Author-email: "D. Edward Scott" <d.edward.scott@outlook.com>
License-Expression: MIT
License-File: LICENSE
Classifier: Operating System :: OS Independent
Classifier: Programming Language :: Python :: 3
Requires-Python: >=3.9
